pvder/DER_check_and_initialize.py
pvder/DER_components.py
pvder/DER_components_single_phase.py
pvder/DER_components_single_phase_constant_Vdc.py
pvder/DER_components_three_phase.py
pvder/DER_components_three_phase_balanced.py
pvder/DER_components_three_phase_constant_Vdc.py
pvder/DER_components_three_phase_no_Vrms_filter.py
pvder/DER_components_three_phase_numba.py
pvder/DER_features.py
pvder/DER_utilities.py
pvder/DER_wrapper.py
pvder/__init__.py
pvder/_version.py
pvder/constants.py
pvder/defaults.py
pvder/dynamic_simulation.py
pvder/exceptionutil.py
pvder/grid_components.py
pvder/logutil.py
pvder/properties.py
pvder/simulation_events.py
pvder/simulation_utilities.py
pvder/specifications.py
pvder/templates.py
pvder/templates_experimental.py
pvder/utilities_experimental.py
pvder/utility_classes.py
pvder/utility_functions.py
pvder/utility_functions_numba.py
pvder/logs/.gitignore
pvder-0.6.0.dist-info/LICENSE
pvder-0.6.0.dist-info/METADATA
pvder-0.6.0.dist-info/WHEEL
pvder-0.6.0.dist-info/top_level.txt
pvder-0.6.0.dist-info/RECORD
