Metadata-Version: 2.1
Name: pvder
Version: 0.6.0
Summary: Utility for simulating PV-DER
Home-page: https://github.com/tdcosim/SolarPV-DER-simulation-tool
Author: Siby Jose Plathottam
Author-email: sibyjackgrove@gmail.com
License: LICENSE.txt
Platform: UNKNOWN
Classifier: License :: OSI Approved :: BSD License
Classifier: Intended Audience :: Science/Research
Classifier: Programming Language :: Python :: 3
Classifier: Programming Language :: Python :: 3.11
License-File: LICENSE
Requires-Dist: scipy (>=1.0.0)
Requires-Dist: numpy (>=1.15.1)
Requires-Dist: matplotlib (>=2.0.2)
Provides-Extra: docs
Requires-Dist: sphinx-rtd-theme ; extra == 'docs'
Requires-Dist: nbsphinx ; extra == 'docs'
Requires-Dist: nbsphinx-link ; extra == 'docs'
Provides-Extra: numba
Requires-Dist: numba (>=0.53.0) ; extra == 'numba'
